Lab93IncomeReporter/__init__.py
Lab93IncomeReporter-0.0.1.dist-info/METADATA
Lab93IncomeReporter-0.0.1.dist-info/WHEEL
Lab93IncomeReporter-0.0.1.dist-info/top_level.txt
Lab93IncomeReporter-0.0.1.dist-info/RECORD
